coursera_autograder/__init__.py
coursera_autograder/main.py
coursera_autograder/utils.py
coursera_autograder/commands/__init__.py
coursera_autograder/commands/common.py
coursera_autograder/commands/config.py
coursera_autograder/commands/get_resource_limits.py
coursera_autograder/commands/get_status.py
coursera_autograder/commands/grade.py
coursera_autograder/commands/list_graders.py
coursera_autograder/commands/oauth2.py
coursera_autograder/commands/update_resource_limits.py
coursera_autograder/commands/upload.py
coursera_autograder-0.1.4.dist-info/LICENSE.txt
coursera_autograder-0.1.4.dist-info/METADATA
coursera_autograder-0.1.4.dist-info/WHEEL
coursera_autograder-0.1.4.dist-info/entry_points.txt
coursera_autograder-0.1.4.dist-info/top_level.txt
coursera_autograder-0.1.4.dist-info/RECORD
