Metadata-Version: 2.1
Name: coursera-autograder
Version: 0.1.4
Summary: A toolkit to help develop asynchronous graders for Coursera          based on docker images.
Home-page: https://github.com/coursera/coursera_autograder
Author: Joseph Li
Author-email: jli@coursera.org
License: Apache
Keywords: grading programming coursera sdk docker cli tool
Classifier: Development Status :: 5 - Production/Stable
Classifier: License :: OSI Approved :: Apache Software License
Classifier: Programming Language :: Python :: 3.7
License-File: LICENSE.txt
